fdpbundle/__init__.py
fdpbundle/cli.py
fdpbundle/client.py
fdpbundle/commands/__init__.py
fdpbundle/commands/apply.py
fdpbundle/commands/deploy.py
fdpbundle/commands/diff.py
fdpbundle/commands/import_cmd.py
fdpbundle/commands/init.py
fdpbundle/commands/validate.py
fdpbundle/templates/README.md
fdpbundle/templates/__init__.py
fdpbundle/templates/bundle.json
fdpbundle/templates/env.example
fdpbundle/templates/gitignore
fdpbundle/templates/gitlab-ci.yml
fdpbundle-0.6.0.dist-info/METADATA
fdpbundle-0.6.0.dist-info/WHEEL
fdpbundle-0.6.0.dist-info/entry_points.txt
fdpbundle-0.6.0.dist-info/top_level.txt
fdpbundle-0.6.0.dist-info/RECORD
