Metadata-Version: 2.4
Name: fdpbundle
Version: 0.6.0
Summary: CLI tool for managing FDP Workflow Engine bundles
Author-email: Hocbt <thaihoc131005@gmail.com>
License: MIT
Project-URL: Homepage, https://gitlab.example.com/data-team/fdpbundle
Project-URL: Documentation, https://gitlab.example.com/data-team/fdpbundle/-/blob/main/README.md
Project-URL: Repository, https://gitlab.example.com/data-team/fdpbundle
Classifier: Development Status :: 4 - Beta
Classifier: Environment :: Console
Classifier: Intended Audience :: Developers
Classifier: License :: OSI Approved :: MIT License
Classifier: Operating System :: OS Independent
Classifier: Programming Language :: Python :: 3
Classifier: Programming Language :: Python :: 3.9
Classifier: Programming Language :: Python :: 3.10
Classifier: Programming Language :: Python :: 3.11
Classifier: Programming Language :: Python :: 3.12
Classifier: Topic :: Software Development :: Build Tools
Requires-Python: >=3.9
Requires-Dist: click>=8.0.0
Requires-Dist: requests>=2.25.0
Requires-Dist: python-dotenv>=0.19.0
Requires-Dist: rich>=12.0.0
Provides-Extra: dev
Requires-Dist: pytest>=7.0.0; extra == "dev"
Requires-Dist: pytest-cov>=4.0.0; extra == "dev"
Requires-Dist: black>=23.0.0; extra == "dev"
Requires-Dist: ruff>=0.1.0; extra == "dev"
